{
    "layers":  {
                   "humanoid":  [
                                    {
                                        "texture":  "vesture:husk"
                                    }
                                ],
                   "humanoid_leggings":  [
                                             {
                                                 "texture":  "vesture:husk"
                                             }
                                         ]
               }
}